setup.py
django_bmemcached/__init__.py
django_bmemcached/memcached.py
django_bmemcached.egg-info/PKG-INFO
django_bmemcached.egg-info/SOURCES.txt
django_bmemcached.egg-info/dependency_links.txt
django_bmemcached.egg-info/requires.txt
django_bmemcached.egg-info/top_level.txt