Metadata-Version: 1.1
Name: django-bmemcached
Version: 0.2.3
Summary: A Django cache backend to use bmemcached module which supports memcached binary protocol with authentication.
Home-page: https://github.com/jaysonsantos/django-bmemcached
Author: Jayson Reis
Author-email: santosdosreis@gmail.com
License: UNKNOWN
Platform: UNKNOWN
Classifier: Development Status :: 4 - Beta
Classifier: License :: OSI Approved :: MIT License
Classifier: Operating System :: OS Independent
